goapfp/__init__.py
goapfp/config/__init__.py
goapfp/config/gaf_line_reader_contracts.py
goapfp/config/obo_line_reader_contracts.py
goapfp/core/__init__.py
goapfp/core/gene_ontology.py
goapfp/core/goterm.py
goapfp/core/semantic_similarity.py
goapfp/eval/__init__.py
goapfp/eval/classification.py
goapfp/io/__init__.py
goapfp/io/abstract_line_reader.py
goapfp/io/gaf_line_reader.py
goapfp/io/gaf_parser.py
goapfp/io/go_annotation.py
goapfp/io/obo_format_error.py
goapfp/io/obo_line_reader.py
goapfp/io/obo_parser.py
goapfp/io/parse_error.py
goapfp/io/stanza.py
goapfp/io/value.py
goapfp-0.0.dev8.dist-info/LICENSE
goapfp-0.0.dev8.dist-info/METADATA
goapfp-0.0.dev8.dist-info/WHEEL
goapfp-0.0.dev8.dist-info/top_level.txt
goapfp-0.0.dev8.dist-info/RECORD
