Metadata-Version: 2.1
Name: goapfp
Version: 0.0.dev8
Summary: Utility tools to work with the Gene Ontology in Python
Author-email: "Alfonso E. Romero" <alfonsoeromero@gmail.com>, Mateo Torres <torresmateo@gmail.com>
Project-URL: Repository, https://github.com/torresmateo/golib/tree/development
Keywords: Gene Ontology,bioinformatics,protein function prediction
Requires-Python: >=3.8
License-File: LICENSE
Requires-Dist: numpy
Requires-Dist: pandas
Requires-Dist: scikit-learn
Requires-Dist: rich
